generateme/DCGan.py
generateme/LinearGan.py
generateme/StyleGan.py
generateme/__init__.py
generateme/app.py
generateme/pywsgi.py
generateme/static/Models/dcGanGeneratorModel.pt
generateme/static/Models/linearGanGeneratorModel.pt
generateme/static/Photos/cat.png
generateme/static/Photos/icon.png
generateme/static/Photos/image.png
generateme/templates/index.html
generateme-0.1.2.dist-info/METADATA
generateme-0.1.2.dist-info/WHEEL
generateme-0.1.2.dist-info/top_level.txt
generateme-0.1.2.dist-info/RECORD
